[
  {
    "message": "str 155 そら個別２"
  },
  {
    "name": "そら",
    "message": "「ひにゃ～、髪、傷んじゃったかも」"
  },
  {
    "message": "髪を結び直した後、何度も髪を気にかけている。"
  },
  {
    "name": "暁",
    "message": "「そんなにすぐ傷むもんなのか？」"
  },
  {
    "name": "そら",
    "message": "「だって、予想いじょーに激しくしこしこしちゃったじゃん」"
  },
  {
    "message": "素で言われると、無性に恥ずかしいんだけど。"
  },
  {
    "name": "そら",
    "message": "「でもさ、にーちゃはそらの髪、気持ちよかったんだよね？」"
  },
  {
    "name": "暁",
    "message": "「ま、まあ、そうかも……」"
  },
  {
    "name": "そら",
    "message": "「気持ちよくなきゃ、あんなすぐに続けてザーメン出さないもんね」"
  },
  {
    "message": "やっぱり、あの妙な匂いの効果もあったのかな？"
  },
  {
    "name": "暁",
    "message": "「……そら、あんまり直接的な言い方するなって」"
  },
  {
    "name": "そら",
    "message": "「直接的……？」"
  },
  {
    "name": "暁",
    "message": "「エッチしてる時ならまだしも、素で色々言われたくないの」"
  },
  {
    "name": "そら",
    "message": "「じゃあ……」"
  },
  {
    "name": "そら",
    "message": "「快感が訪れなければ、短い間隔でお出しになりませんものね……大量のち○ぽ汁を」"
  },
  {
    "name": "暁",
    "message": "「……もういい。ワケ分からん」"
  },
  {
    "name": "そら",
    "message": "「ずっぽし間接的に言ったのに」\\@"
  },
  {
    "name": "暁",
    "message": "「ち○ぽ汁のどこが間接的だ」"
  },
  {
    "name": "そら",
    "message": "「直接的だったら、ザーメンって言うよ！」\\@"
  },
  {
    "name": "暁",
    "message": "「分かった分かった」"
  },
  {
    "message": "この話題はもう止めよう……無意味すぎる。"
  },
  {
    "name": "そら",
    "message": "「ひにゃ～、でも、にーちゃにいっぱいぶっかけられたから、髪と顔がカピカピしてる感じがするよ」"
  },
  {
    "name": "暁",
    "message": "「そ、そっか」"
  },
  {
    "name": "そら",
    "message": "「……でも、にーちゃだから、こんなことされても許してあげるんだからね」"
  },
  {
    "message": "ふっと視線を外して、そんな言葉を口にするそら……気持ち頬が赤くなっているようだった。"
  },
  {
    "name": "そら",
    "message": "「今度は……そらのことも、もっといっぱい気持ちよくしてよ？」"
  },
  {
    "name": "暁",
    "message": "「分かったよ」"
  },
  {
    "message": "さすがに今からもう一回するのは厳しい……何より疲れた……"
  },
  {
    "name": "暁",
    "message": "「じゃあ、そろそろ部屋に戻るか。送ってやるから」"
  },
  {
    "name": "そら",
    "message": "「うん」\\@"
  },
  {
    "message": "返事はしたが、そらは頬の辺りを気にしている。"
  },
  {
    "name": "そら",
    "message": "「ひにゃ～、ちゃんとにーちゃのザーメン拭いたのに、まだお顔がこわばってる感じだよ」"
  },
  {
    "name": "暁",
    "message": "「そ、そっか」"
  },
  {
    "name": "そら",
    "message": "「顔もカピカピ、髪もカピカピ……」"
  },
  {
    "name": "そら",
    "message": "「は！　この状態は！？」\\@"
  },
  {
    "name": "暁",
    "message": "「うん？」"
  },
  {
    "name": "そら",
    "message": "「お前もロウ人形にしてやろうか～！」\\@"
  },
  {
    "name": "暁",
    "message": "「もうそれはいいっつーの！」"
  },
  {
    "message": "本当、そらは退屈させないな……騒がしいけど。"
  }
]