[
  {
    "message": "str 155 都個別７"
  },
  {
    "message": "この日の朝、何の気なしにリビングへ下りてきた俺は、珍しい光景を目にすることとなった。"
  },
  {
    "name": "都",
    "message": "「そ、それで、夜霧さんはどのジャンルが好きなんですか？」"
  },
  {
    "name": "夜霧",
    "message": "「これが一番というのは決められないわね。シチュエーションモノにも、素人モノにも、それぞれ良いところはあると思っているから」"
  },
  {
    "message": "プール脇のソファーに腰掛け、親しげに言葉を交わす都と久千房。"
  },
  {
    "message": "その組み合わせは、簡単に記憶を検索しただけでは前例を思い出すことができず、声を掛けるのを躊躇ってしまう。"
  },
  {
    "name": "夜霧",
    "message": "「……ただ、スカ系だけはほとんど観たことがないわね」"
  },
  {
    "name": "都",
    "message": "「暁お兄ちゃんのおしっこを飲んだわたしが言うのもなんですけど、そこはちょっとハードルが高いですもんね」"
  },
  {
    "name": "夜霧",
    "message": "「の、飲んだっ！？　まさかあなた、小スカ経験者だったの！？」\\@"
  },
  {
    "name": "都",
    "message": "「あぅ……や、やっぱり引いちゃいますよね……」"
  },
  {
    "name": "夜霧",
    "message": "「そういうわけではないけれど、驚いたのは確かね」"
  },
  {
    "name": "都",
    "message": "「すみません……」"
  },
  {
    "name": "夜霧",
    "message": "「謝る必要なんてないけど……その、星月とは他にどんなことをしたの？」"
  },
  {
    "name": "都",
    "message": "「そ、そうですね……ローターをアソコに入れてビーチを歩いたり、ローションを使ったメイドさんプレイとか……ですかね」"
  },
  {
    "name": "夜霧",
    "message": "「……き、気持ちよかった？」"
  },
  {
    "name": "都",
    "message": "「じ、自分が恥ずかしがり屋だってことを忘れてしまうくらい……スゴイです……」"
  },
  {
    "name": "夜霧",
    "message": "「ゴクリ……」\\@"
  },
  {
    "name": "暁",
    "message": "「……アイツらは朝っぱらからなんつー話をしてるんだ」"
  },
  {
    "message": "でも、そういう話が気兼ねなくできるってことが、この家に集められた女の子達にとっては何よりも有意義な“特別”なのだろう。"
  },
  {
    "message": "その証拠に、久千房が誰かとツーショットで話をしているところなんて初めて見たし……"
  },
  {
    "message": "この家に来たばかりの頃は誰に対してもあうあうしていた都が、あんな風に話をしている姿は何となく感慨深い。"
  },
  {
    "name": "圭",
    "message": "「……さながら、娘の成長を見守る父親の心境といったところかな？」"
  },
  {
    "message": "そんな俺の心中を察してか、会長が俺に話し掛けてくる。"
  },
  {
    "name": "暁",
    "message": "「そんな大層なものじゃないですけど……」"
  },
  {
    "name": "暁",
    "message": "「最近の都を見ていると、俺たちがやってきた特訓は無駄じゃなかったんだなって、そう思います」"
  },
  {
    "name": "圭",
    "message": "「京都ちゃんにとって、星月くんという協力者は何よりも心強かったはずだ」"
  },
  {
    "name": "暁",
    "message": "「俺は都と一緒にいられて楽しかったってだけで、実際に頑張っていたのは都ですけどね」"
  },
  {
    "name": "圭",
    "message": "「謙遜は紳士の美徳というものだが……最近は、早朝にも恥ずかしがり屋克服の特訓を行っているんだろう？」"
  },
  {
    "name": "暁",
    "message": "「はい。都がエッチなことに頼らない特訓もやってみたいって言ってくれて」"
  },
  {
    "name": "圭",
    "message": "「やはりか……」"
  },
  {
    "name": "圭",
    "message": "「ここ最近、朝早くにこの家から外出している者がいるという話を聞いて、れもんに調べさせたのだが……」"
  },
  {
    "name": "圭",
    "message": "「それは、帽子を被っていない京都ちゃんと星月くんの二人で、新聞の配達員や散歩をしているご老人に自分たちから挨拶をしていたと聞かされてね」"
  },
  {
    "name": "暁",
    "message": "「早朝なら人通りも少ないし、特訓にはもってこいの時間帯だと思ったんです」"
  },
  {
    "name": "圭",
    "message": "「……なるほど、そういうことだったのか」"
  },
  {
    "name": "暁",
    "message": "「アイツの頑張りには驚かされるばかりですよ」"
  },
  {
    "name": "圭",
    "message": "「恐らく、一緒に頑張ってくれている星月くんのためにも、もっと自分が頑張らなければいけないという思いがあるのだろう」"
  },
  {
    "name": "暁",
    "message": "「…………」"
  },
  {
    "message": "まず間違いなく、都の恥ずかしがり屋は改善の方向に向かっている。"
  },
  {
    "message": "それは、登校日の日に、エッチなことに頼らない状態である程度外を歩けたことからも明らかだ。"
  },
  {
    "message": "そして、この短期間でそれだけの成果が出せているのは、常に向上心を持って、自分に課題を与え続けている都の努力の賜なんだと思う。"
  },
  {
    "name": "圭",
    "message": "「つまり、京都ちゃんは恥ずかしがり屋だが、それ以上に頑張り屋だったということだな」"
  },
  {
    "name": "暁",
    "message": "「……そうですね。都はスゴイやつですよ」"
  },
  {
    "name": "暁",
    "message": "「今まで色々な特訓をやってきましたけど、アイツが俺の提案を断ったのはたった一回しかありませんから」"
  },
  {
    "name": "圭",
    "message": "「その一回が“例のアレ”になるわけか」"
  },
  {
    "name": "暁",
    "message": "「はい……」"
  },
  {
    "name": "圭",
    "message": "「で、星月くんはどう思う？」"
  },
  {
    "name": "暁",
    "message": "「……多分、今なら前回とは違う答えが聞けると思います」"
  },
  {
    "name": "圭",
    "message": "「私も同感だ」\\@"
  },
  {
    "message": "そこで意見を一致させた俺たちは、都を会長の部屋に呼び出すことにした。"
  },
  {
    "name": "都",
    "message": "「はぅ……あぅ……」\\@"
  },
  {
    "message": "突然の呼び出しを受け、床の上で正座をした状態で、子羊のように身体を震わせる都。"
  },
  {
    "message": "まぁ、会長が自分の部屋に誰かを呼ぶということは滅多にないし、緊張してしまうのも当然かもしれない。"
  },
  {
    "name": "圭",
    "message": "「ふむ……怯える京都ちゃんを見ているとドキドキしてきてしまうな……」"
  },
  {
    "name": "都",
    "message": "「──っ！？」\\@"
  },
  {
    "name": "暁",
    "message": "「……会長、都が更に怯えるんで早く話を進めてください」"
  },
  {
    "name": "圭",
    "message": "「そうだな、合意を得ない上での嗜虐は私の主義に反する」"
  },
  {
    "message": "……この人、ひとの話を聞いてるようで聞いてないよな。"
  },
  {
    "name": "圭",
    "message": "「なにも獲って食おうというわけではないし、京都ちゃんももっと楽にしてくれ」"
  },
  {
    "name": "都",
    "message": "「は、はい……」\\@"
  },
  {
    "message": "会長の言葉でほぅっと息を吐き出した都が、正座を崩して女の子座りになる。"
  },
  {
    "name": "圭",
    "message": "「それで、こうして京都ちゃんを呼び出した理由についてなのだが……」"
  },
  {
    "name": "暁",
    "message": "「都も、どうして自分がここに呼ばれたか、何となく察しはついているんじゃないか？」"
  },
  {
    "name": "都",
    "message": "「……わ、わたし、ＡＶに出演させられるんだよね？」"
  },
  {
    "name": "暁",
    "message": "「はぁっ！？」"
  },
  {
    "message": "油断をしていたところに返ってきたあまりにも素っ頓狂な答えに、思わず大声を上げてしまう。"
  },
  {
    "name": "圭",
    "message": "「……何故そう思ったのか聞こう」"
  },
  {
    "name": "都",
    "message": "「えと……さっき夜霧さんが教えてくれたんです。素人モノのＡＶは、最初に豪勢な部屋に誘って興味を引き……」"
  },
  {
    "name": "都",
    "message": "「女の子に『大丈夫大丈夫、全然怖いことなんてないから』と、しきりに安心感を擦り込んでいくものなんだって」"
  },
  {
    "name": "暁",
    "message": "「アイツは都に何を教えてるんだ……」"
  },
  {
    "name": "都",
    "message": "「でも、夜霧さんは早く男女が絡んでいるところが観たいから、冒頭のインタビュー部分はいつも飛ばしてしまうんだそうです」"
  },
  {
    "message": "……さすが久千房さん、玄人感丸出しですね。"
  },
  {
    "name": "圭",
    "message": "「なるほど、千房くんには後日私たちにもＡＶ論を語ってもらうとして……」"
  },
  {
    "name": "圭",
    "message": "「私と星月くんが京都ちゃんを呼び出したのは、スピーチコンテストについての話があったからなんだ」"
  },
  {
    "name": "都",
    "message": "「スピーチコンテスト……ですか？」"
  },
  {
    "name": "圭",
    "message": "「少し前に、興味があったら出てみてはどうだいという提案をしたことがあっただろう？」"
  },
  {
    "name": "都",
    "message": "「は、はい……確か、あの時はお断りさせていただきましたけど……」"
  },
  {
    "name": "圭",
    "message": "「そう、あの時京都ちゃんは自分には無理だと断ったが……」"
  },
  {
    "name": "圭",
    "message": "「実はあの後、星月くんが私のところにきて、京都ちゃんを出場者としてエントリーしておいてくれと頼み込んできたんだ」"
  },
  {
    "name": "都",
    "message": "「っ！？　じゃあもしかして……あの時、会長さんに話があるって言ってたのは……」\\@"
  },
  {
    "name": "暁",
    "message": "「その話をしに行ってたってわけだな」"
  },
  {
    "name": "都",
    "message": "「そ、そうだったんだ……」"
  },
  {
    "name": "暁",
    "message": "「これは勝手な思い込みかもしれないけど……俺にはあの時、都がスピーチコンテストに挑戦したがっているように見えたんだ」"
  },
  {
    "name": "暁",
    "message": "「でも、自分に自信が持てないせいで、みんなに迷惑を掛けてしまった時のことばかりが気になっているだけなんだって」"
  },
  {
    "name": "都",
    "message": "「……っ」"
  },
  {
    "name": "暁",
    "message": "「だからきっと、その考えはすぐに変わる。俺と一緒に恥ずかしがり屋克服の特訓を頑張っていくうちに、いつか、今の自分を試したくなる時がくる」"
  },
  {
    "name": "暁",
    "message": "「そう考えて、都には内緒でエントリーしてもらっていたんだ」"
  },
  {
    "name": "圭",
    "message": "「エントリー後のキャンセルは簡単だが、募集期間外になって『やっぱり出たい』と言われても遅いからね」"
  },
  {
    "name": "都",
    "message": "「じゃあ、暁お兄ちゃんは……」"
  },
  {
    "name": "暁",
    "message": "「ああ、今の都ならこの前とは違う反応が返ってくる。そう思って、この話を打ち明けることにしたんだ」"
  },
  {
    "name": "都",
    "message": "「…………」"
  },
  {
    "message": "一通りの説明が終わったところで、都が静かに目を閉じる。"
  },
  {
    "name": "暁",
    "message": "「…………」"
  },
  {
    "message": "いま、都が何を考えているのかはわからない。"
  },
  {
    "message": "それでも、眉を潜めたり、突然の提案にあたふたしている様子は見受けられない。"
  },
  {
    "name": "都",
    "message": "「じゃあ……もしわたしが出たいと言ったら、参加は可能なんでしょうか？」"
  },
  {
    "name": "圭",
    "message": "「もちろんだ、エントリー自体はすでに完了しているからね」"
  },
  {
    "name": "都",
    "message": "「…………」"
  },
  {
    "name": "都",
    "message": "「それならわたし、スピーチコンテストに出てみたいです」"
  },
  {
    "message": "その言葉が聞けた瞬間、俺は心の中でガッツポーズをとった。"
  },
  {
    "name": "暁",
    "message": "「都ならそう言ってくれると思ってたよ」"
  },
  {
    "name": "都",
    "message": "「エヘヘヘ……」"
  },
  {
    "name": "圭",
    "message": "「では、これは京都ちゃんへの最終確認になるが、この話はあくまでも私と星月くんが勝手に進めてきたことで、もちろん断ることだってできる」"
  },
  {
    "name": "圭",
    "message": "「その上で、京都ちゃんはスピーチコンテストへの出場を決めたということでいいんだね？」"
  },
  {
    "name": "都",
    "message": "「……はい」"
  },
  {
    "name": "都",
    "message": "「正直、今でも本番になって逃げ出さないという自信はありません……」"
  },
  {
    "name": "都",
    "message": "「でも、わたしを信じて背中を押してくれる人がいるなら、やれるところまでやってみたいんです」"
  },
  {
    "name": "圭",
    "message": "「……そうか」"
  },
  {
    "message": "会長は都の言葉に短い返事を返すと、出場者に配られる案内書のような物を手渡した。"
  },
  {
    "name": "圭",
    "message": "「そこに詳しい内容が書かれているから、早めに目を通しておくといい」"
  },
  {
    "name": "都",
    "message": "「ありがとうございます」\\@"
  },
  {
    "name": "圭",
    "message": "「ちなみに、今年のお題は“私”で、スピーチコンテストが行われるのは今日からちょうど一週間後だ」"
  },
  {
    "name": "都",
    "message": "「一週間後……」"
  },
  {
    "name": "圭",
    "message": "「準備期間は充分とは言えないが、私も協力は惜しまないつもりだから頑張ってくれ」"
  },
  {
    "name": "都",
    "message": "「は、はい！　わたし、一生懸命頑張りますっ！！」\\@"
  },
  {
    "message": "都に内緒で話を進めていた、俺たちのお節介──"
  },
  {
    "message": "それが、お節介ではなく下準備に変わったこの日から、スピーチコンテストに向けた準備が始まった。"
  },
  {
    "name": "都",
    "message": "「テーマは“私”って、どんなことを書けばいいのかな……」"
  },
  {
    "name": "そら",
    "message": "「んー、スリーサイズとか、初体験は何時とか……得意なプレイとか？」"
  },
  {
    "name": "都",
    "message": "「それだと、ただのプロフィールになっちゃわないかな？　しかも風俗系の……」"
  },
  {
    "message": "ある時は、親友と一緒に頭を悩ませ──"
  },
  {
    "name": "都",
    "message": "「あ、あの！　夜霧さんみたいにカッコイイ言葉遣いができるようになるには、どうしたらいいんでしょう？」"
  },
  {
    "name": "夜霧",
    "message": "「そんなのは簡単、目の前に居るのが自分の奴隷だと思えばいいのよ」"
  },
  {
    "name": "都",
    "message": "「ど、奴隷っ！？」\\@"
  },
  {
    "message": "またある時は、先輩のアドバイスに耳を傾け──"
  },
  {
    "name": "都",
    "message": "「こここ、こうして今裸になることで……本当に大勢の人の前でも緊張しなくなるんでしょうか……」\\@"
  },
  {
    "name": "鈴",
    "message": "「思い出してみてください、みやちゃん。いつも堂々としている圭ちゃんと、その圭ちゃんのそばにいるわたしの共通点は……？」\\@"
  },
  {
    "name": "都",
    "message": "「っ！？　普段から裸でいることが多いこと……」\\@"
  },
  {
    "message": "そのまたある時は、先輩と一緒に肢体を露わに……"
  },
  {
    "name": "暁",
    "message": "「って、それはさすがにやりすぎだろっ！！」"
  },
  {
    "name": "れもん",
    "message": "「ツッコミたいなら直接言ってあげればいいのに……」"
  },
  {
    "name": "暁",
    "message": "「羽桐か……」"
  },
  {
    "name": "れもん",
    "message": "「だーかーら、私のことは──」"
  },
  {
    "name": "暁",
    "message": "「羽桐と呼び続ける！」"
  },
  {
    "name": "れもん",
    "message": "「ふぁん①」\\@"
  },
  {
    "name": "暁",
    "message": "「俺に呼称を変える気はないってのに、お前もしつこいな……」"
  },
  {
    "name": "れもん",
    "message": "「お約束ですから☆」"
  },
  {
    "message": "さいですか……"
  },
  {
    "name": "れもん",
    "message": "「それより、制服を着てるってことは、これから学園へ行くの？」"
  },
  {
    "name": "暁",
    "message": "「例のスピーチコンテスト関連で、ちょっとな」"
  },
  {
    "name": "れもん",
    "message": "「しかも、柔道着を持参しているところを見ると……今日が柔道部の日で、明日がサッカー部の日なんだっけ？」"
  },
  {
    "name": "暁",
    "message": "「そういうことだ」"
  },
  {
    "name": "れもん",
    "message": "「そんな暁くんの頑張りを知ってか知らずか、都ちゃんも頑張ってるみたいだしね」"
  },
  {
    "name": "暁",
    "message": "「頼もしいことに、みんなも協力してくれているみたいだからな」"
  },
  {
    "name": "れもん",
    "message": "「そういう暁くんは、何かアドバイスしてあげたりしなくていいの？」"
  },
  {
    "name": "暁",
    "message": "「俺が都に教えてやれることなんか無いって。むしろ、いつも教えられているのは俺の方なんだし……」"
  },
  {
    "name": "暁",
    "message": "「それに、今の都なら必ずやり遂げられるって信じてるからな」"
  },
  {
    "name": "れもん",
    "message": "「それは、都ちゃんへの愛？」"
  },
  {
    "name": "暁",
    "message": "「ここで当たり前だろ？　って答えたら格好いいんだろうけど……そうじゃない」"
  },
  {
    "name": "暁",
    "message": "「俺はこの夏を都と過ごして、アイツがどんな人間か知ることができた、それだけだよ」"
  },
  {
    "name": "れもん",
    "message": "「信頼してるんだね、都ちゃんのこと」"
  },
  {
    "name": "暁",
    "message": "「……まぁな」"
  },
  {
    "message": "こうして、改めて口にするのは恥ずかしいけど。"
  },
  {
    "name": "れもん",
    "message": "「だったら、もうちょっと私のことも信頼してくれていいのに……」"
  },
  {
    "message": "言いながら、羽桐が俺の股間に手を伸ばそうとしてくる。"
  },
  {
    "name": "暁",
    "message": "「……その行動から何を信頼しろというのかはわからんが、このボタンのことは信頼してる」"
  },
  {
    "message": "その動きに合わせて、俺が再びお仕置きボタンを構えたところ\\nで──"
  },
  {
    "name": "れもん",
    "message": "「はぅん①　はぅんはぅん①」\\@"
  },
  {
    "message": "一足先に羽桐の口から奇声が上がった。"
  },
  {
    "name": "れもん",
    "message": "「よ、よぎちゃんが呼んでる……んんっ、んっ……」"
  },
  {
    "message": "羽桐は、そのままピクピクと身体を震わせながらリビングを出ていってしまう。"
  },
  {
    "message": "呼び出しボタンの仕組みは未だによくわからないが、あれだけで呼んでいる人間の判別ができるんだから恐ろしい。"
  },
  {
    "name": "都",
    "message": "「うぅ……や、やっぱり……裸を見られるのが女神先輩だけでも恥ずかしいです……」"
  },
  {
    "name": "鈴",
    "message": "「ファイトです！　みやちゃん！！」"
  },
  {
    "name": "暁",
    "message": "「……頑張れ、都」"
  },
  {
    "message": "外から聞こえてきた声に、そんな独り言が口を出る。"
  },
  {
    "message": "特別な時間を過ごす中で仲を深めていった人達の手を借りながら、大きな目標に向かって汗を流している。"
  },
  {
    "message": "そんな後ろ姿が、もっと自分も頑張らなければいけないという気持ちにさせてくれる。"
  },
  {
    "name": "暁",
    "message": "「というわけで、俺も一踏ん張りしますか！」"
  },
  {
    "message": "そうやって、みんなが思い思いの形でスピーチコンテストまでの日々を過ごしていくうちに、あっという間に刻は過ぎ──"
  },
  {
    "message": "本番前日の夜には、都のための壮行会が開かれることとなった。"
  },
  {
    "name": "圭",
    "message": "「それでは、京都ちゃんのスピーチ成功を祈願して、乾杯！」"
  },
  {
    "name": "一同",
    "message": "「かんぱーい♪」"
  },
  {
    "message": "音頭を取った会長に続いて、みんながグラスを傾ける。"
  },
  {
    "message": "テーブルの上には羽桐が腕によりを掛けて作った豪華な料理が並び、久しぶりに全員が揃っての夕食となっていた。"
  },
  {
    "name": "暁",
    "message": "「壮行会を開いてもらえるのはありがたいけど……料理に変な物入れたりしてないだろうな？」"
  },
  {
    "name": "れもん",
    "message": "「もぉ、いくら私でも今日くらいは空気を読むよ。だから、様式美が適用されてるのは暁くんだけ①」\\@"
  },
  {
    "name": "暁",
    "message": "「狙い撃ちかよ！！」"
  },
  {
    "name": "圭",
    "message": "「それで京都ちゃん、とうとう本番前日を迎えたわけだが、準備の方は整っているかい？」"
  },
  {
    "name": "都",
    "message": "「は、はい！　原稿も無事に完成して、今は原稿用紙を見ないでお話しできるように、最後の暗記をしているところです」"
  },
  {
    "name": "圭",
    "message": "「うむ、原稿の暗記は重要なファクターだ。スピーチコンテストは、いかに聴衆の心を掴めるかの勝負だからね」"
  },
  {
    "name": "圭",
    "message": "「下を向いてボソボソとしゃべっているようでは、人の心は掴めない」"
  },
  {
    "name": "そら",
    "message": "「むーん。エムズの会長さんをやってるけーちゃんが言うと説得力があるよ」"
  },
  {
    "name": "圭",
    "message": "「用意された原稿を読むだけのロボット役は、日本の政治家に任せておけばいい」"
  },
  {
    "name": "鈴",
    "message": "「サラッと政治批判が入りましたね」"
  },
  {
    "name": "都",
    "message": "「スピーチは、いかに聴衆の心を掴めるか……」"
  },
  {
    "message": "会長の言葉を真剣に聞いていた都が、自分に言い聞かせるように呟く。"
  },
  {
    "name": "夜霧",
    "message": "「それから、明日はわたしも会場に行くことにしたわ」"
  },
  {
    "name": "暁",
    "message": "「……く、久千房がデレたっ！！」"
  },
  {
    "name": "夜霧",
    "message": "「なっ──」\\@"
  },
  {
    "message": "瞬間、久千房の顔が真っ赤になる。"
  },
  {
    "name": "夜霧",
    "message": "「で、デレ？　アナタは何を言っているの？　沸いたの？」"
  },
  {
    "name": "夜霧",
    "message": "「わたしはただ、明日はたまたま予定がなかったから仕方な\\nく──」"
  },
  {
    "name": "暁",
    "message": "「うんうん、たまたまなんだよな」"
  },
  {
    "name": "夜霧",
    "message": "「クッ……星月にこんな顔をさせるなんて人生最大の汚点だわ……」"
  },
  {
    "name": "暁",
    "message": "「どんだけ低いんだよ……俺の存在価値……」"
  },
  {
    "name": "鈴",
    "message": "「ふふふ、いいじゃないですか。明日はみんなでみやちゃんを応援しましょう」"
  },
  {
    "name": "そら",
    "message": "「そらも、講堂に横断幕をかかげて精一杯応援するよ！」"
  },
  {
    "name": "れもん",
    "message": "「じゃあ、横断幕の用意は私に任せて？　一晩でやっておくから☆」"
  },
  {
    "name": "圭",
    "message": "「その気持ちは尊重したいところだが、スピーチ中に声を上げたり騒いだりするのはマナー違反になるから気をつけるように」"
  },
  {
    "name": "そら・れもん",
    "message": "「はーい……」"
  },
  {
    "message": "事前の注意に二人がシュンとなったところで、壮行会の主役である都が席を立った。"
  },
  {
    "name": "都",
    "message": "「あ、あの……皆さん、今日はわたしのために素敵な壮行会を開いてくださって、ありがとうございます」"
  },
  {
    "name": "都",
    "message": "「明日のことを考えると、やっぱり緊張しちゃいますけど……」"
  },
  {
    "name": "都",
    "message": "「わたし、この一週間皆さんとたくさんお話しできて、すごく楽しかったです」"
  },
  {
    "name": "都",
    "message": "「だ、だから、明日は一生懸命頑張りますので、応援よろしくお願いしますっ！」"
  },
  {
    "message": "そんな風に都が明日の抱負を口にすると、周りから自然と拍手が上がった。"
  },
  {
    "name": "圭",
    "message": "「では、最後を星月くんに締めてもらって食事にするとしよう」"
  },
  {
    "name": "暁",
    "message": "「えっ！？　お、俺ですか？」"
  },
  {
    "name": "圭",
    "message": "「キミは京都ちゃんの彼氏で、スピーチコンテストへの出場を促した発起人だろう？」"
  },
  {
    "name": "暁",
    "message": "「それはそうですけど……」"
  },
  {
    "name": "都",
    "message": "「さ、暁お兄ちゃん……」"
  },
  {
    "message": "都は期待の眼差しを向けているけど、緊張で身体が強ばっているのがわかる。"
  },
  {
    "message": "それならここは一つ……"
  },
  {
    "name": "暁",
    "message": "「……わかりました」"
  },
  {
    "message": "俺は覚悟を決めると、さっきの都と同じように席を立った。"
  },
  {
    "name": "暁",
    "message": "「えぇー、皆さんそれぞれが都に言いたいことがあると思いますが、俺がいま都に言いたいことは一つです」"
  },
  {
    "name": "圭",
    "message": "「ほほぅ……」"
  },
  {
    "name": "暁",
    "message": "「……ゴメンな都。実は俺、今までお前に黙っていたことがあるんだ」"
  },
  {
    "name": "都",
    "message": "「えっ……」"
  },
  {
    "message": "突然声のトーンを落として真剣な表情を浮かべる俺を見て、都の表情が強ばる。"
  },
  {
    "name": "暁",
    "message": "「都……お前は、お前はな……」"
  },
  {
    "name": "都",
    "message": "「ちょっ、あにょ……さ、暁お兄ちゃん？」"
  },
  {
    "message": "そして、限界まで思わせぶりな空気を引っ張ったところで──"
  },
  {
    "name": "暁",
    "message": "\\f30;「芽上先輩の名前を間違えて覚えてしまっているんだ！！」\\f26;\\@"
  },
  {
    "message": "夏休み前からずっと喉に引っ掛かっていた間違いを指摘した。"
  },
  {
    "name": "都",
    "message": "「ぇ……」"
  },
  {
    "name": "暁",
    "message": "「芽上先輩の本名は\\f30;“めがみすず”\\f26;じゃなく\\f30;“めかみすず”\\f26;だ！」"
  },
  {
    "name": "都",
    "message": "「えぇっ！？　そ、そうなの！？」\\@"
  },
  {
    "message": "俺の言葉に周りがきょとんとした顔を浮かべる中、やはり都だけが狙い通りの反応を示した。"
  },
  {
    "name": "そら",
    "message": "「かなちゃん……鈴先輩の名字、女神だと思ってたの？」"
  },
  {
    "name": "都",
    "message": "「う、うん……」"
  },
  {
    "name": "そら",
    "message": "「そら、かなちゃんなりの愛称なのかと思ってたよ……」"
  },
  {
    "name": "鈴",
    "message": "「私もです……」"
  },
  {
    "name": "夜霧",
    "message": "「というより、なんで今？」"
  },
  {
    "name": "暁",
    "message": "「いやー、最初にスルーしたら指摘するタイミングを逃しちゃって、言うならここしかないと思ってさ」"
  },
  {
    "name": "圭",
    "message": "「ハッハッハ。なるほど、星月くんらしいな」"
  },
  {
    "name": "都",
    "message": "「す、すみません、芽上先輩！　わたし、今までとんでもない失礼を……」"
  },
  {
    "name": "鈴",
    "message": "「そんな、みやちゃんが謝ることはありません」"
  },
  {
    "name": "鈴",
    "message": "「愛称で呼ばれた方が仲良しさんみたいですし、これまで通り\\n“女神先輩”と呼んでください」"
  },
  {
    "name": "都",
    "message": "「はぅ……女神先輩マジ女神……」"
  },
  {
    "name": "れもん",
    "message": "「ふむふむ……都ちゃんはそらちゃんとのカップリング一択だと思ってたけど、鈴×都もアリ？」\\@"
  },
  {
    "name": "暁",
    "message": "「はは……」"
  },
  {
    "message": "なんだか、思わぬ方向に話がシフトしたような気がするけど、少しは都の緊張を解せたかな。"
  },
  {
    "name": "暁",
    "message": "「というわけで、俺の言葉はこれで終わりです」"
  },
  {
    "name": "そら",
    "message": "「うわっ、なにそれ……もっとずっぽし気の利いたセリフはなかったの？」"
  },
  {
    "name": "圭",
    "message": "「いや、これ以上の言葉はないだろう。星月くんは、今更京都ちゃんに掛ける言葉など無いと言っているんだからね」"
  },
  {
    "name": "暁",
    "message": "「はい。この一週間、都がどれだけ頑張ってきたかは知っていますから」"
  },
  {
    "name": "都",
    "message": "「暁お兄ちゃん……」"
  },
  {
    "name": "暁",
    "message": "「だから、明日は頑張れよ、都」"
  },
  {
    "name": "都",
    "message": "「うん！」\\@"
  },
  {
    "message": "そこから、スピーチコンテストの壮行会は夕食会へと形を変え……"
  },
  {
    "message": "明日に差し支えがあってはいけないということで、１時間ほどでお開きとなった。"
  },
  {
    "name": "暁",
    "message": "「ついに明日が本番か……」"
  },
  {
    "message": "やっと、その大きさに慣れてきたベッドに寝転がって、明日のことを考える。"
  },
  {
    "message": "都にスピーチコンテストへの出場を促そうと決めた日から、俺なりにやれることはやってきたつもりだけど、その結果は直前までわからない。"
  },
  {
    "message": "だから、明日もやれるだけのことはやっておこう。"
  },
  {
    "message": "俺が今の都にしてやれるのは、最高の舞台を用意してやることくらいなのだから──"
  },
  {
    "name": "暁",
    "message": "「……んっ？」"
  },
  {
    "message": "そろそろ電気を消そうと思ったところで、唐突にノックの音が聞こえてくる。"
  },
  {
    "name": "都",
    "message": "「暁お兄ちゃん、まだ起きてる？」"
  },
  {
    "name": "暁",
    "message": "「都か、入ってきていいぞ」"
  },
  {
    "name": "都",
    "message": "「うん、それじゃあお邪魔するね……」"
  },
  {
    "message": "それからすぐにドアが開いて、都が部屋の中に入ってきた。"
  },
  {
    "name": "都",
    "message": "「と、隣に座ってもいいかな？」"
  },
  {
    "name": "暁",
    "message": "「ああ……」"
  },
  {
    "message": "都が隣に腰を下ろすと、ほのかにソープの匂いが漂ってくる。"
  },
  {
    "message": "どうやら、お風呂に入ってから来てくれたらしい。"
  },
  {
    "name": "暁",
    "message": "「でも、おしっこはさっき出したばかりだから、今は出ないと思うぞ？」"
  },
  {
    "name": "都",
    "message": "「わ、わたしは別に、おしっこをもらいに来たわけじゃないよ！」"
  },
  {
    "name": "暁",
    "message": "「えっ？　違うのか？」"
  },
  {
    "name": "都",
    "message": "「はぅん……今度はわたしに“おしっ[娘/こ]”のイメージが……」"
  },
  {
    "message": "本当は、都が部屋を訪ねてきてくれた理由は何となくわかっている。"
  },
  {
    "message": "わかっているからこそ、どうしてもくすぐったくなってしまう。"
  },
  {
    "name": "暁",
    "message": "「わるいわるい、冗談だって」"
  },
  {
    "name": "都",
    "message": "「むー、暁お兄ちゃんがそういうイジワルを言うのは、わたしがお尻にチュッパチョプスを刺したことを根に持ってるからだね？」"
  },
  {
    "message": "その話をされると、別のところがくすぐったくなってしまうので勘弁してください……"
  },
  {
    "name": "暁",
    "message": "「それで、部屋に来たってことは、何か俺に話があったんだろ？」"
  },
  {
    "name": "都",
    "message": "「う、うん……今のうちに、暁お兄ちゃんにお礼を言っておこうと思って」\\@"
  },
  {
    "name": "暁",
    "message": "「……お礼？」"
  },
  {
    "name": "都",
    "message": "「会長さんにお願いして、スピーチコンテストに応募してくれていたことだよ」"
  },
  {
    "name": "暁",
    "message": "「ああ、そのことか」"
  },
  {
    "name": "都",
    "message": "「暁お兄ちゃんが言ってた通り、会長さんからスピーチコンテストの話を聞かされたとき……本当はわたし『出てみたい』って思ったの」"
  },
  {
    "name": "都",
    "message": "「でも『わたしなんかには絶対に無理だ』って、決めつけてた……」"
  },
  {
    "name": "暁",
    "message": "「じゃあ、俺の考えは間違ってなかったんだな」"
  },
  {
    "name": "都",
    "message": "「うん……」\\@"
  },
  {
    "name": "都",
    "message": "「でも、あれから暁お兄ちゃんとたくさん特訓をして、ちょっとだけ自分に自信が持てた」"
  },
  {
    "name": "都",
    "message": "「そして、今の自分を試してみたいって思い始めてたのも本当だから」"
  },
  {
    "name": "暁",
    "message": "「……そっか」"
  },
  {
    "name": "都",
    "message": "「だから、わたしのことを理解してくれて……信じてくれてありがとう、暁お兄ちゃん」"
  },
  {
    "name": "暁",
    "message": "「そんなの当然だろ？」"
  },
  {
    "name": "都",
    "message": "「ぇ……」"
  },
  {
    "name": "暁",
    "message": "「都のことは、都のことを好きになった俺が“二番目”によく知ってるんだからさ」"
  },
  {
    "name": "都",
    "message": "「エヘヘ……やっぱり暁お兄ちゃんはカッコイイな」"
  },
  {
    "name": "暁",
    "message": "「俺には、今の都の方が格好良く見えるけどな」"
  },
  {
    "name": "都",
    "message": "「ううん……わたしは、暁お兄ちゃんが思ってるほどカッコよくなんてないよ」"
  },
  {
    "name": "都",
    "message": "「前にも言ったけど、わたしは暁お兄ちゃんがいてくれたから頑張れた。それは、今でも変わってないよ」"
  },
  {
    "name": "暁",
    "message": "「都……」"
  },
  {
    "name": "都",
    "message": "「だからね……今度はわたし一人なんだって考えると、怖くなって……」"
  },
  {
    "name": "都",
    "message": "「本番の日が近づいてくればくるほど、緊張してきちゃって……」"
  },
  {
    "message": "顔を伏せながらそう口にする都の身体は、小さく震えていた。"
  },
  {
    "name": "都",
    "message": "「だから、暁お兄ちゃんから勇気……もらってもいいかな？」"
  },
  {
    "name": "暁",
    "message": "「……ああ」"
  },
  {
    "message": "都の言葉に短い返事をして、俺は小さな手を握った。"
  },
  {
    "name": "都",
    "message": "「暁お兄ちゃん……」"
  },
  {
    "name": "暁",
    "message": "「都……」"
  },
  {
    "message": "名前を呼び合い、その身体を抱きしめる。"
  },
  {
    "name": "暁",
    "message": "「……キス、してもいいか？」"
  },
  {
    "name": "都",
    "message": "「うん……わたしもしてほしい」"
  },
  {
    "message": "こちらに主導権を委ねるように目を瞑った都の唇に、そっと自分の唇を重ねる。"
  },
  {
    "name": "都",
    "message": "「んっ……」"
  },
  {
    "message": "久しぶりに触れた都の唇は程よく柔らかく、確かな体温が安心感を与えてくれる。"
  },
  {
    "name": "都",
    "message": "「んんっ……」"
  },
  {
    "message": "都が、俺と同じように安心感を得られるように──"
  },
  {
    "message": "勇気が物質化できるなら、いくらでも俺から持っていってほしい。"
  },
  {
    "message": "そんなことを願いながら、自分の温もりを伝えていく。"
  },
  {
    "name": "都",
    "message": "「んふっ…………はっ……」"
  },
  {
    "message": "すると、１０秒と経たないうちに都の方から唇を離してしまう。"
  },
  {
    "name": "暁",
    "message": "「……その、もういいのか？」"
  },
  {
    "name": "都",
    "message": "「うん……こういうキスは、これでお終い」"
  },
  {
    "name": "暁",
    "message": "「こういうキス？」"
  },
  {
    "name": "都",
    "message": "「なんていうかね、今日は……付き合い始めのカップルがするような、初初しいキスがしてみたかったの」"
  },
  {
    "name": "都",
    "message": "「わたしって、お兄ちゃんとエッチなことをするときは、最初からスイッチが入っちゃってることが多いから……」"
  },
  {
    "name": "暁",
    "message": "「なるほど……」"
  },
  {
    "message": "そういえば、海ではいきなり濃厚なベロチューをされたっけ。"
  },
  {
    "name": "暁",
    "message": "「でも俺、都は激しいキスの方が好きなんだと思ってたよ」"
  },
  {
    "name": "都",
    "message": "「だから……次は恋人同士がするエッチなキス……」"
  },
  {
    "message": "“やっぱりか”と苦笑していると、今度は都の方から唇を重ねてくる。"
  },
  {
    "name": "都",
    "message": "「んふっ……ちゅっ、ちゅく……んっ……ちゅぷっ……」"
  },
  {
    "message": "そのまま舌先が唇を割り開き、都の舌が口内に侵入してくる。"
  },
  {
    "message": "舌使いに自信のある都ならではの、アクティブなキス。"
  },
  {
    "name": "都",
    "message": "「んふふ……おにーひゃんの舌、つかまえた……んっ……ちゅくっ、ちゅっ……れろっ……」"
  },
  {
    "message": "敏感な口内を何度もまさぐられ、むず痒い快感が背筋を走る。"
  },
  {
    "name": "都",
    "message": "「ちゅぷっ、ちゅっ……はっ……おにーひゃんの唾液、きょうはエッチなあじ……んっ……」"
  },
  {
    "name": "都",
    "message": "「らから……暁お兄ちゃんの唾液、もっと飲ませて？　んっ……んふっ、ちゅっ……んくっ……んくっ……」"
  },
  {
    "message": "キツく身体を抱きしめて唾液を交換していると、徐々に脳が痺れ始めていく。"
  },
  {
    "name": "都",
    "message": "「んはっ……ちゃんと舌も吸ってあげる……んっ……ちゅくっ、ちゅ……ちゅうーーーっ！」"
  },
  {
    "name": "都",
    "message": "「はむっ、んっ……ちゅうぅぅ……れろっ……んっ……ズズッ……」"
  },
  {
    "message": "こちらが応戦すればするほど都の舌は激しい動きを見せ、更に俺を求めてくる。"
  },
  {
    "name": "都",
    "message": "「じゅるる……んっ、れろっ、ちゅっ……おにーひゃん……んっ……ちゅくっ、ちゅうぅぅっ！！」"
  },
  {
    "message": "息が苦しくなり、最後に激しく舌を吸い立てられたところで、どちらからともなく顔を離した。"
  },
  {
    "name": "都",
    "message": "「んはっ……はぁ……はぁ……はぁ……」"
  },
  {
    "message": "今までで一番激しいキスの余韻に浸りながら、お互いに呼吸を整えていく。"
  },
  {
    "name": "都",
    "message": "「んんっ、んっ……わたし、やっぱりこっちのキスの方が好き……」"
  },
  {
    "name": "暁",
    "message": "「都とするキスって、なんでこんなに気持ちいいんだろうな」"
  },
  {
    "name": "都",
    "message": "「エヘヘ……そう言ってもらえるとペロリスト冥利に尽きるよ……」"
  },
  {
    "message": "素直な感想を口にすると、都は本当に嬉しそうに笑ってくれる。"
  },
  {
    "name": "暁",
    "message": "「じゃあ、今度は俺が都のことを気持ちよくする番だよな」"
  },
  {
    "name": "都",
    "message": "「よ、よろしくお願いします……」"
  }
]